mqt_naviz-0.2.0.dist-info/METADATA
mqt_naviz-0.2.0.dist-info/WHEEL
naviz/__init__.py
naviz/naviz.cp313-win_amd64.pyd
mqt_naviz-0.2.0.dist-info/RECORD
