Metadata-Version: 2.4
Name: mqt-naviz
Version: 0.2.0
Classifier: Development Status :: 4 - Beta
Classifier: Intended Audience :: Science/Research
Classifier: Natural Language :: English
Classifier: Operating System :: MacOS
Classifier: Operating System :: Microsoft :: Windows
Classifier: Operating System :: POSIX :: Linux
Classifier: Programming Language :: Python
Classifier: Programming Language :: Python :: 3 :: Only
Classifier: Programming Language :: Python :: 3.10
Classifier: Programming Language :: Python :: 3.11
Classifier: Programming Language :: Python :: 3.12
Classifier: Programming Language :: Python :: 3.13
Classifier: Programming Language :: Python :: 3.14
Classifier: Programming Language :: Rust
Classifier: Topic :: Scientific/Engineering :: Electronic Design Automation (EDA)
Summary: A Visualizer for Neutral Atom Quantum Computers
Keywords: MQT,quantum-computing,design-automation,compiler,visualization,neutral-atoms
Author-email: Nico Petzendorfer <nico.petzendorfer@tum.de>, Yannick Stade <yannick.stade@tum.de>, Daniel Haag <daniel.haag@tum.de>
License-Expression: MIT
Requires-Python: >=3.10
Project-URL: Homepage, https://github.com/munich-quantum-toolkit/naviz
Project-URL: Documentation, https://mqt.readthedocs.io/projects/naviz
Project-URL: Issues, https://github.com/munich-quantum-toolkit/naviz/issues
Project-URL: Discussions, https://github.com/munich-quantum-toolkit/naviz/discussions
